{
  "name": "bruno_config",
  "version": "1",
  "items": [
    {
      "type": "http",
      "name": "get_token",
      "filename": "get_token.bru",
      "seq": 1,
      "request": {
        "url": "{{ai_auth_url}}/oauth/token",
        "method": "POST",
        "headers": [
          {
            "name": "Content-Type",
            "value": "application/x-www-form-urlencoded",
            "enabled": true
          }
        ],
        "params": [],
        "body": {
          "mode": "formUrlEncoded",
          "formUrlEncoded": [
            {
              "name": "grant_type",
              "value": "client_credentials",
              "enabled": true
            },
            {
              "name": "client_id",
              "value": "{{client_id}}",
              "enabled": true
            },
            {
              "name": "client_secret",
              "value": "{{client_secret}}",
              "enabled": true
            }
          ],
          "multipartForm": [],
          "file": []
        },
        "script": {
          "res": "if (res.getStatus() == 200) {\n  bru.setEnvVar(\"access_token\", res.body.access_token);\n}"
        },
        "vars": {},
        "assertions": [],
        "tests": "",
        "docs": "",
        "auth": {
          "mode": "none"
        }
      }
    },
    {
      "type": "http",
      "name": "health",
      "filename": "health.bru",
      "seq": 2,
      "request": {
        "url": "{{ai_api_url}}/api/v1/healthz",
        "method": "GET",
        "headers": [],
        "params": [],
        "body": {
          "mode": "none",
          "formUrlEncoded": [],
          "multipartForm": [],
          "file": []
        },
        "script": {},
        "vars": {},
        "assertions": [],
        "tests": "",
        "docs": "",
        "auth": {
          "mode": "bearer",
          "bearer": {
            "token": "{{access_token}}"
          }
        }
      }
    },
    {
      "type": "folder",
      "name": "02_deployments",
      "filename": "02_deployments",
      "items": [
        {
          "type": "http",
          "name": "create_configuration",
          "filename": "create_configuration.bru",
          "seq": 3,
          "request": {
            "url": "{{ai_api_url}}/v2/lm/configurations",
            "method": "POST",
            "headers": [
              {
                "name": "AI-Resource-Group",
                "value": "{{resource_group}}",
                "enabled": true
              }
            ],
            "params": [],
            "body": {
              "mode": "json",
              "json": "{\n  \"name\": \"orchestration-config\",\n  \"executableId\": \"orchestration\",\n  \"scenarioId\": \"orchestration\"\n}",
              "formUrlEncoded": [],
              "multipartForm": [],
              "file": []
            },
            "script": {},
            "vars": {},
            "assertions": [],
            "tests": "",
            "docs": "",
            "auth": {
              "mode": "bearer",
              "bearer": {
                "token": "{{access_token}}"
              }
            }
          }
        },
        {
          "type": "http",
          "name": "create_deployment",
          "filename": "create_deployment.bru",
          "seq": 5,
          "request": {
            "url": "{{ai_api_url}}/v2/lm/deployments",
            "method": "POST",
            "headers": [
              {
                "name": "AI-Resource-Group",
                "value": "{{resource_group}}",
                "enabled": true
              }
            ],
            "params": [],
            "body": {
              "mode": "json",
              "json": "{\n  \"ttl\": \"24H\",\n  \"configurationId\": \"<CONFIGURATION_ID>\"\n}",
              "formUrlEncoded": [],
              "multipartForm": [],
              "file": []
            },
            "script": {},
            "vars": {},
            "assertions": [],
            "tests": "",
            "docs": "",
            "auth": {
              "mode": "bearer",
              "bearer": {
                "token": "{{access_token}}"
              }
            }
          }
        },
        {
          "type": "http",
          "name": "delete_deployment_id",
          "filename": "delete_deployment_id.bru",
          "seq": 9,
          "request": {
            "url": "{{ai_api_url}}/v2/lm/deployments/<DEPLOYMENT_ID>",
            "method": "DELETE",
            "headers": [
              {
                "name": "AI-Resource-Group",
                "value": "{{resource_group}}",
                "enabled": true
              }
            ],
            "params": [],
            "body": {
              "mode": "none",
              "json": "{\n  \"ttl\": \"24H\",\n  \"configurationId\": \"<CONFIGURATION_ID>\"\n}",
              "formUrlEncoded": [],
              "multipartForm": [],
              "file": []
            },
            "script": {},
            "vars": {},
            "assertions": [],
            "tests": "",
            "docs": "",
            "auth": {
              "mode": "bearer",
              "bearer": {
                "token": "{{access_token}}"
              }
            }
          }
        },
        {
          "type": "http",
          "name": "get_configuration",
          "filename": "get_configuration.bru",
          "seq": 4,
          "request": {
            "url": "{{ai_api_url}}/v2/lm/configurations",
            "method": "GET",
            "headers": [
              {
                "name": "AI-Resource-Group",
                "value": "{{resource_group}}",
                "enabled": true
              }
            ],
            "params": [],
            "body": {
              "mode": "none",
              "formUrlEncoded": [],
              "multipartForm": [],
              "file": []
            },
            "script": {},
            "vars": {},
            "assertions": [],
            "tests": "",
            "docs": "",
            "auth": {
              "mode": "bearer",
              "bearer": {
                "token": "{{access_token}}"
              }
            }
          }
        },
        {
          "type": "http",
          "name": "get_deployment",
          "filename": "get_deployment.bru",
          "seq": 6,
          "request": {
            "url": "{{ai_api_url}}/v2/lm/deployments",
            "method": "GET",
            "headers": [
              {
                "name": "AI-Resource-Group",
                "value": "{{resource_group}}",
                "enabled": true
              }
            ],
            "params": [],
            "body": {
              "mode": "none",
              "json": "{\n  \"ttl\": \"24H\",\n  \"configurationId\": \"<CONFIGURATION_ID>\"\n}",
              "formUrlEncoded": [],
              "multipartForm": [],
              "file": []
            },
            "script": {},
            "vars": {},
            "assertions": [],
            "tests": "",
            "docs": "",
            "auth": {
              "mode": "bearer",
              "bearer": {
                "token": "{{access_token}}"
              }
            }
          }
        },
        {
          "type": "http",
          "name": "get_deployment_id",
          "filename": "get_deployment_id.bru",
          "seq": 7,
          "request": {
            "url": "{{ai_api_url}}/v2/lm/deployments/<>DEPLOYMENT_ID",
            "method": "GET",
            "headers": [
              {
                "name": "AI-Resource-Group",
                "value": "{{resource_group}}",
                "enabled": true
              }
            ],
            "params": [],
            "body": {
              "mode": "none",
              "json": "{\n  \"ttl\": \"24H\",\n  \"configurationId\": \"<CONFIGURATION_ID>\"\n}",
              "formUrlEncoded": [],
              "multipartForm": [],
              "file": []
            },
            "script": {},
            "vars": {},
            "assertions": [],
            "tests": "",
            "docs": "",
            "auth": {
              "mode": "bearer",
              "bearer": {
                "token": "{{access_token}}"
              }
            }
          }
        },
        {
          "type": "http",
          "name": "get_scenario",
          "filename": "get_scenario.bru",
          "seq": 1,
          "request": {
            "url": "{{ai_api_url}}/v2/lm/scenarios",
            "method": "GET",
            "headers": [
              {
                "name": "AI-Resource-Group",
                "value": "{{resource_group}}",
                "enabled": true
              }
            ],
            "params": [],
            "body": {
              "mode": "none",
              "formUrlEncoded": [],
              "multipartForm": [],
              "file": []
            },
            "script": {},
            "vars": {},
            "assertions": [],
            "tests": "",
            "docs": "",
            "auth": {
              "mode": "bearer",
              "bearer": {
                "token": "{{access_token}}"
              }
            }
          }
        },
        {
          "type": "http",
          "name": "get_scenario_executable",
          "filename": "get_scenario_executable.bru",
          "seq": 2,
          "request": {
            "url": "{{ai_api_url}}/v2/lm/scenarios/orchestration/executables",
            "method": "GET",
            "headers": [
              {
                "name": "AI-Resource-Group",
                "value": "{{resource_group}}",
                "enabled": true
              }
            ],
            "params": [],
            "body": {
              "mode": "none",
              "formUrlEncoded": [],
              "multipartForm": [],
              "file": []
            },
            "script": {},
            "vars": {},
            "assertions": [],
            "tests": "",
            "docs": "",
            "auth": {
              "mode": "bearer",
              "bearer": {
                "token": "{{access_token}}"
              }
            }
          }
        },
        {
          "type": "http",
          "name": "stop_deployment_id",
          "filename": "stop_deployment_id.bru",
          "seq": 8,
          "request": {
            "url": "{{ai_api_url}}/v2/lm/deployments/<DEPLOYMENT_ID>",
            "method": "PATCH",
            "headers": [
              {
                "name": "AI-Resource-Group",
                "value": "{{resource_group}}",
                "enabled": true
              }
            ],
            "params": [],
            "body": {
              "mode": "json",
              "json": "{\n  \"targetStatus\": \"STOPPED\"\n}",
              "formUrlEncoded": [],
              "multipartForm": [],
              "file": []
            },
            "script": {},
            "vars": {},
            "assertions": [],
            "tests": "",
            "docs": "",
            "auth": {
              "mode": "bearer",
              "bearer": {
                "token": "{{access_token}}"
              }
            }
          }
        }
      ]
    },
    {
      "type": "folder",
      "name": "03_generic_secret",
      "filename": "03_generic_secret",
      "items": [
        {
          "type": "http",
          "name": "create",
          "filename": "create.bru",
          "seq": 2,
          "request": {
            "url": "{{ai_api_url}}/v2/admin/secrets",
            "method": "POST",
            "headers": [
              {
                "name": "AI-Resource-Group",
                "value": "{{resource_group}}",
                "enabled": true
              }
            ],
            "params": [],
            "body": {
              "mode": "json",
              "json": "{\n  \"name\": \"<name>\",\n  \"data\": {\n    \"type\": \"SFRUUA==\",\n    \"description\": \"<DESCRIPTION>\",\n    \"clientId\": \"<base64encodedValueOfClientId>\",\n    \"authentication\": \"<AUTHENTICATION>\",\n    \"tokenServiceURL\": \"<base64encodedValueOfTokenServiceUrl>\",\n    \"password\": \"<base64encodedValueOfPassword>\",\n    \"proxyType\": \"PROXY\",\n    \"url\": \"<base64encodedValueOfUrl>\",\n    \"tokenServiceURLType\": \"TOKENSERVICE\",\n    \"user\": \"<base64encodedValueOfUser>\",\n    \"clientSecret\": \"<base64encodedValueOfClientSecret>\",\n    \"scope\": \"<SCOPE>\"\n  },\n  \"labels\": [\n    {\n      \"key\": \"ext.ai.sap.com/document-grounding\",\n      \"value\": \"true\"\n    }\n  ]\n}",
              "formUrlEncoded": [],
              "multipartForm": [],
              "file": []
            },
            "script": {},
            "vars": {},
            "assertions": [],
            "tests": "",
            "docs": "",
            "auth": {
              "mode": "bearer",
              "bearer": {
                "token": "{{access_token}}"
              }
            }
          }
        },
        {
          "type": "http",
          "name": "delete",
          "filename": "delete.bru",
          "seq": 3,
          "request": {
            "url": "{{ai_api_url}}/v2/admin/secrets/canary-rg-secret",
            "method": "DELETE",
            "headers": [
              {
                "name": "AI-Resource-Group",
                "value": "{{resource_group}}",
                "enabled": true
              }
            ],
            "params": [],
            "body": {
              "mode": "none",
              "formUrlEncoded": [],
              "multipartForm": [],
              "file": []
            },
            "script": {},
            "vars": {},
            "assertions": [],
            "tests": "",
            "docs": "",
            "auth": {
              "mode": "bearer",
              "bearer": {
                "token": "{{access_token}}"
              }
            }
          }
        },
        {
          "type": "http",
          "name": "get_all",
          "filename": "get_all.bru",
          "seq": 1,
          "request": {
            "url": "{{ai_api_url}}/v2/admin/secrets",
            "method": "GET",
            "headers": [
              {
                "name": "AI-Resource-Group",
                "value": "{{resource_group}}",
                "enabled": true
              }
            ],
            "params": [],
            "body": {
              "mode": "none",
              "formUrlEncoded": [],
              "multipartForm": [],
              "file": []
            },
            "script": {},
            "vars": {},
            "assertions": [],
            "tests": "",
            "docs": "",
            "auth": {
              "mode": "bearer",
              "bearer": {
                "token": "{{access_token}}"
              }
            }
          }
        },
        {
          "type": "http",
          "name": "update",
          "filename": "update.bru",
          "seq": 4,
          "request": {
            "url": "{{ai_api_url}}/v2/admin/secrets/canary-rg-secret",
            "method": "PATCH",
            "headers": [
              {
                "name": "AI-Resource-Group",
                "value": "{{resource_group}}",
                "enabled": true
              }
            ],
            "params": [],
            "body": {
              "mode": "json",
              "json": "{\n  \"data\": {\n    \"clientId\": \"<CLIENTID>\"\n  }\n}",
              "formUrlEncoded": [],
              "multipartForm": [],
              "file": []
            },
            "script": {},
            "vars": {},
            "assertions": [],
            "tests": "",
            "docs": "",
            "auth": {
              "mode": "bearer",
              "bearer": {
                "token": "{{access_token}}"
              }
            }
          }
        }
      ]
    },
    {
      "type": "folder",
      "name": "06_vector",
      "filename": "06_vector",
      "items": [
        {
          "type": "http",
          "name": "create_collections",
          "filename": "create_collections.bru",
          "seq": 2,
          "request": {
            "url": "{{ai_api_url}}{{common_endpoint}}/vector/collections",
            "method": "POST",
            "headers": [
              {
                "name": "AI-Resource-Group",
                "value": "{{resource_group}}",
                "enabled": true
              }
            ],
            "params": [],
            "body": {
              "mode": "json",
              "json": "{\n  \"title\": \"test-canary-collection\",\n  \"embeddingConfig\": {\n    \"modelName\": \"text-embedding-ada-002-v2\"\n  },\n  \"metadata\": [\n    {\n      \"key\": \"purpose\",\n      \"value\": [\n        \"demonstration\"\n      ]\n    },\n    {\n      \"key\": \"a-random-key\",\n      \"value\": [\n        \"hello world!\"\n      ]\n    }\n  ]\n}",
              "formUrlEncoded": [],
              "multipartForm": [],
              "file": []
            },
            "script": {},
            "vars": {},
            "assertions": [],
            "tests": "",
            "docs": "",
            "auth": {
              "mode": "bearer",
              "bearer": {
                "token": "{{access_token}}"
              }
            }
          }
        },
        {
          "type": "http",
          "name": "create_documents",
          "filename": "create_documents.bru",
          "seq": 5,
          "request": {
            "url": "{{ai_api_url}}{{common_endpoint}}/vector/collections/<COLLECTION_ID>/documents",
            "method": "POST",
            "headers": [
              {
                "name": "AI-Resource-Group",
                "value": "{{resource_group}}",
                "enabled": true
              }
            ],
            "params": [],
            "body": {
              "mode": "json",
              "json": "{\n  \"documents\": [\n    {\n      \"metadata\": [\n        {\n          \"key\": \"url\",\n          \"value\": [\n            \"http://hello.com\",\n            \"123\"\n          ]\n        }\n      ],\n      \"chunks\": [\n        {\n          \"content\": \"Joule is the AI copilot that truly understands your business. Joule revolutionizes how you interact with your SAP business systems, making every touchpoint count and every task simpler.\",\n          \"metadata\": [\n            {\n              \"key\": \"index\",\n              \"value\": [\n                \"1\"\n              ]\n            }\n          ]\n        },\n        {\n          \"content\": \"It enables the companion of the Intelligent Enterprise, guiding you through content discovery within SAP Ecosystem, and giving a transparent role-based access to the relevant processes from everywhere. This is the one assistant experience, a unified and delightful user experience across SAP’s Ǯ solution portfolio.\",\n          \"metadata\": [\n            {\n              \"key\": \"index\",\n              \"value\": [\n                \"2\"\n              ]\n            }\n          ]\n        }\n      ]\n    }\n  ]\n}",
              "formUrlEncoded": [],
              "multipartForm": [],
              "file": []
            },
            "script": {},
            "vars": {},
            "assertions": [],
            "tests": "",
            "docs": "",
            "auth": {
              "mode": "bearer",
              "bearer": {
                "token": "{{access_token}}"
              }
            }
          }
        },
        {
          "type": "http",
          "name": "delete_collection_by_id",
          "filename": "delete_collection_by_id.bru",
          "seq": 12,
          "request": {
            "url": "{{ai_api_url}}{{common_endpoint}}/vector/collections/<COLLECTION_ID>",
            "method": "DELETE",
            "headers": [
              {
                "name": "AI-Resource-Group",
                "value": "{{resource_group}}",
                "enabled": true
              }
            ],
            "params": [],
            "body": {
              "mode": "none",
              "formUrlEncoded": [],
              "multipartForm": [],
              "file": []
            },
            "script": {},
            "vars": {},
            "assertions": [],
            "tests": "",
            "docs": "",
            "auth": {
              "mode": "bearer",
              "bearer": {
                "token": "{{access_token}}"
              }
            }
          }
        },
        {
          "type": "http",
          "name": "delete_documents_by_id",
          "filename": "delete_documents_by_id.bru",
          "seq": 11,
          "request": {
            "url": "{{ai_api_url}}{{common_endpoint}}/vector/collections/<COLLECTION_ID>/documents/<DOCUMENT_ID>",
            "method": "DELETE",
            "headers": [
              {
                "name": "AI-Resource-Group",
                "value": "{{resource_group}}",
                "enabled": true
              }
            ],
            "params": [],
            "body": {
              "mode": "none",
              "formUrlEncoded": [],
              "multipartForm": [],
              "file": []
            },
            "script": {},
            "vars": {},
            "assertions": [],
            "tests": "",
            "docs": "",
            "auth": {
              "mode": "bearer",
              "bearer": {
                "token": "{{access_token}}"
              }
            }
          }
        },
        {
          "type": "http",
          "name": "get_all_collections",
          "filename": "get_all_collections.bru",
          "seq": 1,
          "request": {
            "url": "{{ai_api_url}}{{common_endpoint}}/vector/collections",
            "method": "GET",
            "headers": [
              {
                "name": "AI-Resource-Group",
                "value": "{{resource_group}}",
                "enabled": true
              }
            ],
            "params": [],
            "body": {
              "mode": "none",
              "formUrlEncoded": [],
              "multipartForm": [],
              "file": []
            },
            "script": {},
            "vars": {},
            "assertions": [],
            "tests": "",
            "docs": "",
            "auth": {
              "mode": "bearer",
              "bearer": {
                "token": "{{access_token}}"
              }
            }
          }
        },
        {
          "type": "http",
          "name": "get_all_documents_by_collection_id",
          "filename": "get_all_documents_by_collection_id.bru",
          "seq": 6,
          "request": {
            "url": "{{ai_api_url}}{{common_endpoint}}/vector/collections/<COLLECTION_ID>/documents",
            "method": "GET",
            "headers": [
              {
                "name": "AI-Resource-Group",
                "value": "{{resource_group}}",
                "enabled": true
              }
            ],
            "params": [],
            "body": {
              "mode": "none",
              "formUrlEncoded": [],
              "multipartForm": [],
              "file": []
            },
            "script": {},
            "vars": {},
            "assertions": [],
            "tests": "",
            "docs": "",
            "auth": {
              "mode": "bearer",
              "bearer": {
                "token": "{{access_token}}"
              }
            }
          }
        },
        {
          "type": "http",
          "name": "get_collection_by_id",
          "filename": "get_collection_by_id.bru",
          "seq": 4,
          "request": {
            "url": "{{ai_api_url}}/v2/lm/document-grounding/vector/collections/<COLLECTION_ID>",
            "method": "GET",
            "headers": [
              {
                "name": "AI-Resource-Group",
                "value": "{{resource_group}}",
                "enabled": true
              }
            ],
            "params": [],
            "body": {
              "mode": "none",
              "formUrlEncoded": [],
              "multipartForm": [],
              "file": []
            },
            "script": {},
            "vars": {},
            "assertions": [],
            "tests": "",
            "docs": "",
            "auth": {
              "mode": "bearer",
              "bearer": {
                "token": "{{access_token}}"
              }
            }
          }
        },
        {
          "type": "http",
          "name": "get_collection_creation_status_by_id",
          "filename": "get_collection_creation_status_by_id.bru",
          "seq": 3,
          "request": {
            "url": "{{ai_api_url}}{{common_endpoint}}/vector/collections/<COLLECTION_ID>/creationStatus",
            "method": "GET",
            "headers": [
              {
                "name": "AI-Resource-Group",
                "value": "{{resource_group}}",
                "enabled": true
              }
            ],
            "params": [],
            "body": {
              "mode": "none",
              "formUrlEncoded": [],
              "multipartForm": [],
              "file": []
            },
            "script": {},
            "vars": {},
            "assertions": [],
            "tests": "",
            "docs": "",
            "auth": {
              "mode": "bearer",
              "bearer": {
                "token": "{{access_token}}"
              }
            }
          }
        },
        {
          "type": "http",
          "name": "get_collection_deletion_status_by_id",
          "filename": "get_collection_deletion_status_by_id.bru",
          "seq": 13,
          "request": {
            "url": "{{ai_api_url}}{{common_endpoint}}/vector/collections/<COLLECTION_ID>/deletionStatus",
            "method": "GET",
            "headers": [
              {
                "name": "AI-Resource-Group",
                "value": "{{resource_group}}",
                "enabled": true
              }
            ],
            "params": [],
            "body": {
              "mode": "none",
              "formUrlEncoded": [],
              "multipartForm": [],
              "file": []
            },
            "script": {},
            "vars": {},
            "assertions": [],
            "tests": "",
            "docs": "",
            "auth": {
              "mode": "bearer",
              "bearer": {
                "token": "{{access_token}}"
              }
            }
          }
        },
        {
          "type": "http",
          "name": "get_documents_by_id",
          "filename": "get_documents_by_id.bru",
          "seq": 7,
          "request": {
            "url": "{{ai_api_url}}{{common_endpoint}}/vector/collections/<COLLECTION_ID>/documents/<DOCUMENT_ID>",
            "method": "GET",
            "headers": [
              {
                "name": "AI-Resource-Group",
                "value": "{{resource_group}}",
                "enabled": true
              }
            ],
            "params": [],
            "body": {
              "mode": "none",
              "formUrlEncoded": [],
              "multipartForm": [],
              "file": []
            },
            "script": {},
            "vars": {},
            "assertions": [],
            "tests": "",
            "docs": "",
            "auth": {
              "mode": "bearer",
              "bearer": {
                "token": "{{access_token}}"
              }
            }
          }
        },
        {
          "type": "http",
          "name": "insert_documents",
          "filename": "insert_documents.bru",
          "seq": 9,
          "request": {
            "url": "{{ai_api_url}}{{common_endpoint}}/vector/collections/<COLLECTION_ID>/documents",
            "method": "PATCH",
            "headers": [
              {
                "name": "AI-Resource-Group",
                "value": "{{resource_group}}",
                "enabled": true
              }
            ],
            "params": [],
            "body": {
              "mode": "json",
              "json": "{\n  \"documents\": [\n    {\n      \"id\": \"<DOCUMENT_ID>\",\n      \"metadata\": [\n        {\n          \"key\": \"url\",\n          \"value\": [\"http://hello1.com\"]\n        },\n        {\n          \"key\": \"test-insert\",\n          \"value\": [\"123\"]\n        }\n      ],\n      \"chunks\": [\n        {\n          \"content\": \"Joule is not the AI copilot that truly understands your business. Joule revolutionizes how you interact with your SAP business systems, making every touchpoint count and every task simpler.\",\n          \"metadata\": [\n            {\n              \"key\": \"index\",\n              \"value\": [\n                \"1\"\n              ]\n            }\n          ]\n        },\n        {\n          \"content\": \"It enables the companion of the Intelligent Enterprise, guiding you through content discovery within SAP Ecosystem, and giving a transparent role-based access to the relevant processes from everywhere. This is the one assistant experience, a unified and delightful user experience across SAP’s Ǯ solution portfolio.\",\n          \"metadata\": [\n            {\n              \"key\": \"index\",\n              \"value\": [\n                \"2\"\n              ]\n            }\n          ]\n        }\n      ]\n    }\n  ]\n}",
              "formUrlEncoded": [],
              "multipartForm": [],
              "file": []
            },
            "script": {},
            "vars": {},
            "assertions": [],
            "tests": "",
            "docs": "",
            "auth": {
              "mode": "bearer",
              "bearer": {
                "token": "{{access_token}}"
              }
            }
          }
        },
        {
          "type": "http",
          "name": "search",
          "filename": "search.bru",
          "seq": 10,
          "request": {
            "url": "{{ai_api_url}}{{common_endpoint}}/vector/search",
            "method": "POST",
            "headers": [
              {
                "name": "AI-Resource-Group",
                "value": "{{resource_group}}",
                "enabled": true
              }
            ],
            "params": [],
            "body": {
              "mode": "json",
              "json": "{\n  \"query\": \"is Joule an AI Copilot?\",\n  \"filters\": [\n    {\n      \"id\": \"string\",\n      \"collectionIds\": [\n        \"<COLLECTION_ID>\"\n      ],\n      \"configuration\": {},\n      \"collectionMetadata\": [],\n      \"documentMetadata\": [\n        {\n          \"key\": \"url\",\n          \"value\": [\n            \"http://hello1.com\"\n          ],\n          \"selectMode\": [\"ignoreIfKeyAbsent\"]\n        }\n      ],\n      \"chunkMetadata\": []\n    }\n  ]\n}",
              "formUrlEncoded": [],
              "multipartForm": [],
              "file": []
            },
            "script": {},
            "vars": {},
            "assertions": [],
            "tests": "",
            "docs": "",
            "auth": {
              "mode": "bearer",
              "bearer": {
                "token": "{{access_token}}"
              }
            }
          }
        },
        {
          "type": "http",
          "name": "update_documents",
          "filename": "update_documents.bru",
          "seq": 8,
          "request": {
            "url": "{{ai_api_url}}{{common_endpoint}}/vector/collections/<COLLECTION_ID>/documents",
            "method": "PATCH",
            "headers": [
              {
                "name": "AI-Resource-Group",
                "value": "{{resource_group}}",
                "enabled": true
              }
            ],
            "params": [],
            "body": {
              "mode": "json",
              "json": "{\n  \"documents\": [\n    {\n      \"id\": \"<DOCUMENT_ID>\",\n      \"metadata\": [\n        {\n          \"key\": \"url\",\n          \"value\": [\"http://hello1.com\"]\n        }\n      ],\n      \"chunks\": [\n        {\n          \"content\": \"Joule is not the AI copilot that truly understands your business. Joule revolutionizes how you interact with your SAP business systems, making every touchpoint count and every task simpler.\",\n          \"metadata\": [\n            {\n              \"key\": \"index\",\n              \"value\": [\n                \"1\"\n              ]\n            }\n          ]\n        },\n        {\n          \"content\": \"It enables the companion of the Intelligent Enterprise, guiding you through content discovery within SAP Ecosystem, and giving a transparent role-based access to the relevant processes from everywhere. This is the one assistant experience, a unified and delightful user experience across SAP’s Ǯ solution portfolio.\",\n          \"metadata\": [\n            {\n              \"key\": \"index\",\n              \"value\": [\n                \"2\"\n              ]\n            }\n          ]\n        }\n      ]\n    }\n  ]\n}",
              "formUrlEncoded": [],
              "multipartForm": [],
              "file": []
            },
            "script": {},
            "vars": {},
            "assertions": [],
            "tests": "",
            "docs": "",
            "auth": {
              "mode": "bearer",
              "bearer": {
                "token": "{{access_token}}"
              }
            }
          }
        }
      ]
    },
    {
      "type": "folder",
      "name": "01_resource_group",
      "filename": "01_resource_group",
      "items": [
        {
          "type": "http",
          "name": "create",
          "filename": "create.bru",
          "seq": 1,
          "request": {
            "url": "{{ai_api_url}}/v2/admin/resourceGroups",
            "method": "POST",
            "headers": [],
            "params": [],
            "body": {
              "mode": "json",
              "json": "{\n  \"resourceGroupId\": \"{{resource_group}}\",\n  \"labels\": [\n    {\n      \"key\": \"ext.ai.sap.com/document-grounding\",\n      \"value\": \"true\"\n    }\n  ]\n}",
              "formUrlEncoded": [],
              "multipartForm": [],
              "file": []
            },
            "script": {},
            "vars": {},
            "assertions": [],
            "tests": "",
            "docs": "",
            "auth": {
              "mode": "bearer",
              "bearer": {
                "token": "{{access_token}}"
              }
            }
          }
        },
        {
          "type": "http",
          "name": "delete_by_id",
          "filename": "delete_by_id.bru",
          "seq": 4,
          "request": {
            "url": "{{ai_api_url}}/v2/admin/resourceGroups/{{resource_group}}",
            "method": "DELETE",
            "headers": [],
            "params": [],
            "body": {
              "mode": "none",
              "formUrlEncoded": [],
              "multipartForm": [],
              "file": []
            },
            "script": {},
            "vars": {},
            "assertions": [],
            "tests": "",
            "docs": "",
            "auth": {
              "mode": "bearer",
              "bearer": {
                "token": "{{access_token}}"
              }
            }
          }
        },
        {
          "type": "http",
          "name": "get",
          "filename": "get.bru",
          "seq": 2,
          "request": {
            "url": "{{ai_api_url}}/v2/admin/resourceGroups",
            "method": "GET",
            "headers": [],
            "params": [],
            "body": {
              "mode": "none",
              "formUrlEncoded": [],
              "multipartForm": [],
              "file": []
            },
            "script": {},
            "vars": {},
            "assertions": [],
            "tests": "",
            "docs": "",
            "auth": {
              "mode": "bearer",
              "bearer": {
                "token": "{{access_token}}"
              }
            }
          }
        },
        {
          "type": "http",
          "name": "get_by_id",
          "filename": "get_by_id.bru",
          "seq": 3,
          "request": {
            "url": "{{ai_api_url}}/v2/admin/resourceGroups/{{resource_group}}",
            "method": "GET",
            "headers": [],
            "params": [],
            "body": {
              "mode": "none",
              "formUrlEncoded": [],
              "multipartForm": [],
              "file": []
            },
            "script": {},
            "vars": {},
            "assertions": [],
            "tests": "",
            "docs": "",
            "auth": {
              "mode": "bearer",
              "bearer": {
                "token": "{{access_token}}"
              }
            }
          }
        }
      ]
    },
    {
      "type": "folder",
      "name": "04_pipeline",
      "filename": "04_pipeline",
      "items": [
        {
          "type": "http",
          "name": "create_pipeline",
          "filename": "create_pipeline.bru",
          "seq": 1,
          "request": {
            "url": "{{ai_api_url}}{{common_endpoint}}/pipelines",
            "method": "POST",
            "headers": [
              {
                "name": "Content-Type",
                "value": "application/json",
                "enabled": true
              },
              {
                "name": "AI-Resource-Group",
                "value": "{{resource_group}}",
                "enabled": true
              }
            ],
            "params": [],
            "body": {
              "mode": "json",
              "json": "{\n  \"type\": \"MSSharePoint\",\n  \"configuration\": {\n    \"destination\": \"<generic_secret_name>\",\n    \"sharePoint\": {\n      \"site\": {\n        \"name\": \"<sharepoint_site_name>\",\n        \"includePaths\": [\n          \"/<folder_name>\"\n        ]\n      }\n    }\n  }\n}",
              "formUrlEncoded": [],
              "multipartForm": [],
              "file": []
            },
            "script": {},
            "vars": {},
            "assertions": [],
            "tests": "",
            "docs": "",
            "auth": {
              "mode": "bearer",
              "bearer": {
                "token": "{{access_token}}"
              }
            }
          }
        },
        {
          "type": "http",
          "name": "delete_pipeline_by_pipeline_id",
          "filename": "delete_pipeline_by_pipeline_id.bru",
          "seq": 5,
          "request": {
            "url": "{{ai_api_url}}{{common_endpoint}}/pipelines/<PIPELINE_ID>",
            "method": "DELETE",
            "headers": [
              {
                "name": "AI-Resource-Group",
                "value": "{{resource_group}}",
                "enabled": true
              }
            ],
            "params": [],
            "body": {
              "mode": "none",
              "formUrlEncoded": [],
              "multipartForm": [],
              "file": []
            },
            "script": {},
            "vars": {},
            "assertions": [],
            "tests": "",
            "docs": "",
            "auth": {
              "mode": "bearer",
              "bearer": {
                "token": "{{access_token}}"
              }
            }
          }
        },
        {
          "type": "http",
          "name": "get_all_pipelines",
          "filename": "get_all_pipelines.bru",
          "seq": 2,
          "request": {
            "url": "{{ai_api_url}}{{common_endpoint}}/pipelines",
            "method": "GET",
            "headers": [
              {
                "name": "AI-Resource-Group",
                "value": "{{resource_group}}",
                "enabled": true
              }
            ],
            "params": [],
            "body": {
              "mode": "none",
              "formUrlEncoded": [],
              "multipartForm": [],
              "file": []
            },
            "script": {},
            "vars": {},
            "assertions": [],
            "tests": "",
            "docs": "",
            "auth": {
              "mode": "bearer",
              "bearer": {
                "token": "{{access_token}}"
              }
            }
          }
        },
        {
          "type": "http",
          "name": "get_pipeline_by_pipeline_id",
          "filename": "get_pipeline_by_pipeline_id.bru",
          "seq": 3,
          "request": {
            "url": "{{ai_api_url}}{{common_endpoint}}/pipelines/<PIPELINE_ID>",
            "method": "GET",
            "headers": [
              {
                "name": "AI-Resource-Group",
                "value": "{{resource_group}}",
                "enabled": true
              }
            ],
            "params": [],
            "body": {
              "mode": "none",
              "formUrlEncoded": [],
              "multipartForm": [],
              "file": []
            },
            "script": {},
            "vars": {},
            "assertions": [],
            "tests": "",
            "docs": "",
            "auth": {
              "mode": "bearer",
              "bearer": {
                "token": "{{access_token}}"
              }
            }
          }
        },
        {
          "type": "http",
          "name": "get_pipeline_status_by_pipeline_id",
          "filename": "get_pipeline_status_by_pipeline_id.bru",
          "seq": 4,
          "request": {
            "url": "{{ai_api_url}}{{common_endpoint}}/pipelines/<PIPELINE_ID>/status",
            "method": "GET",
            "headers": [
              {
                "name": "AI-Resource-Group",
                "value": "{{resource_group}}",
                "enabled": true
              }
            ],
            "params": [],
            "body": {
              "mode": "none",
              "formUrlEncoded": [],
              "multipartForm": [],
              "file": []
            },
            "script": {},
            "vars": {},
            "assertions": [],
            "tests": "",
            "docs": "",
            "auth": {
              "mode": "bearer",
              "bearer": {
                "token": "{{access_token}}"
              }
            }
          }
        }
      ]
    },
    {
      "type": "folder",
      "name": "07_retrieval",
      "filename": "07_retrieval",
      "items": [
        {
          "type": "http",
          "name": "dataRepositories by id",
          "filename": "dataRepositories by id.bru",
          "seq": 2,
          "request": {
            "url": "{{ai_api_url}}{{common_endpoint}}/retrieval/dataRepositories/<DATAREPOSITORY_ID>",
            "method": "GET",
            "headers": [
              {
                "name": "AI-Resource-Group",
                "value": "{{resource_group}}",
                "enabled": true
              }
            ],
            "params": [],
            "body": {
              "mode": "none",
              "formUrlEncoded": [],
              "multipartForm": [],
              "file": []
            },
            "script": {},
            "vars": {},
            "assertions": [],
            "tests": "",
            "docs": "",
            "auth": {
              "mode": "bearer",
              "bearer": {
                "token": "{{access_token}}"
              }
            }
          }
        },
        {
          "type": "http",
          "name": "dataRepositories",
          "filename": "dataRepositories.bru",
          "seq": 1,
          "request": {
            "url": "{{ai_api_url}}{{common_endpoint}}/retrieval/dataRepositories",
            "method": "GET",
            "headers": [
              {
                "name": "AI-Resource-Group",
                "value": "{{resource_group}}",
                "enabled": true
              }
            ],
            "params": [],
            "body": {
              "mode": "none",
              "formUrlEncoded": [],
              "multipartForm": [],
              "file": []
            },
            "script": {},
            "vars": {},
            "assertions": [],
            "tests": "",
            "docs": "",
            "auth": {
              "mode": "bearer",
              "bearer": {
                "token": "{{access_token}}"
              }
            }
          }
        },
        {
          "type": "http",
          "name": "retrieval_pipeline",
          "filename": "retrieval_pipeline.bru",
          "seq": 3,
          "request": {
            "url": "{{ai_api_url}}{{common_endpoint}}/retrieval/search",
            "method": "POST",
            "headers": [
              {
                "name": "AI-Resource-Group",
                "value": "{{resource_group}}",
                "enabled": true
              },
              {
                "name": "Content-Type",
                "value": "application/json",
                "enabled": true
              }
            ],
            "params": [],
            "body": {
              "mode": "json",
              "json": "{\n  \"query\": \"what is AI106 about and who are the presenters?\",\n  \"filters\": [\n    {\n      \"id\": \"string\",\n      \"searchConfiguration\": {},\n      \"dataRepositories\": [\n        \"<DATAREPOSITORY_ID>\"\n      ],\n      \"dataRepositoryType\": \"vector\",\n      \"dataRepositoryMetadata\": [],\n      \"documentMetadata\": [],\n      \"chunkMetadata\": []\n    }\n  ]\n}",
              "formUrlEncoded": [],
              "multipartForm": [],
              "file": []
            },
            "script": {},
            "vars": {},
            "assertions": [],
            "tests": "",
            "docs": "",
            "auth": {
              "mode": "bearer",
              "bearer": {
                "token": "{{access_token}}"
              }
            }
          }
        },
        {
          "type": "http",
          "name": "retrieval_vector",
          "filename": "retrieval_vector.bru",
          "seq": 4,
          "request": {
            "url": "{{ai_api_url}}{{common_endpoint}}/retrieval/search",
            "method": "POST",
            "headers": [
              {
                "name": "AI-Resource-Group",
                "value": "{{resource_group}}",
                "enabled": true
              },
              {
                "name": "Content-Type",
                "value": "application/json",
                "enabled": true
              }
            ],
            "params": [],
            "body": {
              "mode": "json",
              "json": "{\n  \"query\": \"is joule an ai copilot?\",\n  \"filters\": [\n    {\n      \"id\": \"string\",\n      \"searchConfiguration\": {\n        \"maxChunkCount\": 1\n      },\n      \"dataRepositories\": [\n        \"<DATA_REPOSITORYID>\"\n      ],\n      \"dataRepositoryType\": \"vector\",\n      \"dataRepositoryMetadata\": [],\n      \"documentMetadata\": [],\n      \"chunkMetadata\": []\n    }\n  ]\n}",
              "formUrlEncoded": [],
              "multipartForm": [],
              "file": []
            },
            "script": {},
            "vars": {},
            "assertions": [],
            "tests": "",
            "docs": "",
            "auth": {
              "mode": "bearer",
              "bearer": {
                "token": "{{access_token}}"
              }
            }
          }
        }
      ]
    },
    {
      "type": "folder",
      "name": "05_orchestration",
      "filename": "05_orchestration",
      "items": [
        {
          "type": "http",
          "name": "completion",
          "filename": "completion.bru",
          "seq": 1,
          "request": {
            "url": "{{orchestration_service_url}}/v2/completion",
            "method": "POST",
            "headers": [
              {
                "name": "ai-resource-group",
                "value": "{{resource_group}}",
                "enabled": true
              }
            ],
            "params": [],
            "body": {
              "mode": "json",
              "json": "{ \n\"config\": {\n    \"modules\": {\n      \"prompt_templating\": {\n        \"prompt\": {\n          \"template\": [\n            {\n              \"role\": \"assistant\",\n              \"content\": \"Support Issue: '''{{?support-issue}}'''\\n Context Information: '''{{?issue-context}}'''\"\n            },\n            {\n              \"role\": \"system\",\n              \"content\": \"You are a helpful support assistant. Your task is to help answer a given support issue. \\n Your proceed as follows: \\n First, check if the provided context information answers the issue. Based on the result do one of the following: \\n a) If yes, provide an answer based on the provided context information in form of an email and then finish. \\n b) If no, only if you cannot answer the issue you summarize the issue for the human support team. Ignore the context information in this case and provide your answer only based on the support issue. Answer in the following format:\\n - Sentiment: [your sentiment analysis] \\n - Key Theme: [theme of the support issue] \\n - Contact: [any contact information available in the issue]\"\n            }\n          ]\n        },\n        \"model\": {\n          \"name\": \"gpt-4o\",\n          \"params\": {\n            \"max_completion_tokens\": 300,\n            \"temperature\": 0.1,\n            \"frequency_penalty\": 0,\n            \"presence_penalty\": 0\n          }\n        }\n      },\n      \"filtering\": {\n        \"input\": {\n          \"filters\": [\n            {\n              \"type\": \"azure_content_safety\",\n              \"config\": {\n                \"hate\": 4,\n                \"self_harm\": 4,\n                \"sexual\": 4,\n                \"violence\": 4\n              }\n            }\n          ]\n        },\n        \"output\": {\n          \"filters\": [\n            {\n              \"type\": \"azure_content_safety\",\n              \"config\": {\n                \"hate\": 0,\n                \"self_harm\": 0,\n                \"sexual\": 0,\n                \"violence\": 0\n              }\n            }\n          ]\n        }\n      },\n      \"masking\": {\n        \"providers\": [\n          {\n            \"type\": \"sap_data_privacy_integration\",\n            \"method\": \"pseudonymization\",\n            \"entities\": [\n              {\n                \"type\": \"profile-email\"\n              },\n              {\n                \"type\": \"profile-person\"\n              },\n              {\n                \"type\": \"profile-phone\"\n              },\n              {\n                \"type\": \"profile-address\"\n              }\n            ]\n          }\n        ]\n      },\n      \"grounding\": {\n        \"type\": \"document_grounding_service\",\n        \"config\": {\n          \"filters\": [\n            {\n              \"id\": \"helpRepo\",\n              \"data_repositories\": [\n                \"*\"\n              ],\n              \"search_config\": {\n                \"max_chunk_count\": 3\n              },\n              \"data_repository_type\": \"help.sap.com\"\n            }\n          ],\n          \"placeholders\": {\n            \"input\": [\n              \"support-issue\"\n            ],\n            \"output\": \"issue-context\"\n          }\n        }\n      },\n      \"translation\": {\n          \"input\": {\n              \"type\": \"sap_document_translation\",\n              \"config\": {\n                  \"source_language\": \"de-DE\",\n                  \"target_language\": \"en-US\"\n              }\n          },\n          \"output\": {\n              \"type\": \"sap_document_translation\",\n              \"config\": {\n                  \"source_language\": \"en-US\",\n                  \"target_language\": \"de-DE\"\n              }\n          }\n      }\n    }\n  },\n  \"placeholder_values\": {\n    \"support-issue\": \"Betreff: Unterstützung benötigt \\nNachricht: \\nHallo, ich benötige Unterstützung mit SAP Signavio. Insbesondere möchte ich Benachrichtigungen im SAP Signavio Process Manager konfigurieren. Bitte kontaktieren Sie mich mit unter Jane.Janeson@gmx.net.\"\n  }\n}\n\n\n",
              "formUrlEncoded": [],
              "multipartForm": [],
              "file": []
            },
            "script": {},
            "vars": {},
            "assertions": [],
            "tests": "",
            "docs": "",
            "auth": {
              "mode": "bearer",
              "bearer": {
                "token": "{{access_token}}"
              }
            }
          }
        },
        {
          "type": "http",
          "name": "completion_help",
          "filename": "completion_help.bru",
          "seq": 2,
          "request": {
            "url": "{{orchestration_service_url}}/v2/completion",
            "method": "POST",
            "headers": [
              {
                "name": "ai-resource-group",
                "value": "{{resource_group}}",
                "enabled": true
              }
            ],
            "params": [],
            "body": {
              "mode": "json",
              "json": "{\n  \"config\": {\n    \"modules\": {\n      \"prompt_templating\": {\n        \"prompt\": {\n          \"template\": [\n            {\n              \"role\": \"user\",\n              \"content\": \"You are a helpful assistant for any queries for SAP Teched 2024.\\nAnswer the grounding request by providing relevant answers that fit to the request.\\n\\nRequest: {{?groundingRequest}}\\n\\nReports: {{?groundingOutput}}\"\n            }\n          ]\n        },\n        \"model\": {\n          \"name\": \"gemini-2.5-pro\",\n          \"params\": {\n            \"max_completion_tokens\": 300\n          }\n        }\n      },\n\n      \"grounding\": {\n        \"type\": \"document_grounding_service\",\n        \"config\": {\n          \"filters\": [\n            {\n              \"id\": \"filter1\",\n              \"data_repositories\": [\"*\"],\n              \"search_config\": {},\n              \"data_repository_type\": \"help.sap.com\"\n            }\n          ],\n          \"placeholders\": {\n            \"input\": [\"groundingRequest\"],\n            \"output\": \"groundingOutput\"\n          }\n        }\n      },\n\n      \"filtering\": {\n        \"input\": {\n          \"filters\": [\n            {\n              \"type\": \"azure_content_safety\",\n              \"config\": {\n                \"hate\": 2,\n                \"self_harm\": 2,\n                \"sexual\": 2,\n                \"violence\": 2\n              }\n            }\n          ]\n        },\n        \"output\": {\n          \"filters\": [\n            {\n              \"type\": \"azure_content_safety\",\n              \"config\": {\n                \"hate\": 2,\n                \"self_harm\": 2,\n                \"sexual\": 2,\n                \"violence\": 2\n              }\n            }\n          ]\n        }\n      }\n    }\n  },\n\n  \"placeholder_values\": {\n    \"groundingRequest\": \"what is joule?\"\n  }\n}",
              "formUrlEncoded": [],
              "multipartForm": [],
              "file": []
            },
            "script": {},
            "vars": {},
            "assertions": [],
            "tests": "",
            "docs": "",
            "auth": {
              "mode": "bearer",
              "bearer": {
                "token": "{{access_token}}"
              }
            }
          }
        },
        {
          "type": "http",
          "name": "get_foundation_models",
          "filename": "get_foundation_models.bru",
          "seq": 3,
          "request": {
            "url": "{{ai_api_url}}/v2/lm/scenarios/foundation-models/models",
            "method": "GET",
            "headers": [
              {
                "name": "AI-Resource-Group",
                "value": "{{resource_group}}",
                "enabled": true
              }
            ],
            "params": [],
            "body": {
              "mode": "none",
              "formUrlEncoded": [],
              "multipartForm": [],
              "file": []
            },
            "script": {},
            "vars": {},
            "assertions": [],
            "tests": "",
            "docs": "",
            "auth": {
              "mode": "bearer",
              "bearer": {
                "token": "{{access_token}}"
              }
            }
          }
        }
      ]
    },
    {
      "type": "folder",
      "name": "08_consume_model",
      "filename": "08_consume_model",
      "items": [
        {
          "type": "http",
          "name": "direct_model_usage",
          "filename": "direct_model_usage.bru",
          "seq": 2,
          "request": {
            "url": "{{orchestration_service_url}}/v2/completion",
            "method": "POST",
            "headers": [
              {
                "name": "ai-resource-group",
                "value": "{{resource_group}}",
                "enabled": true
              },
              {
                "name": "Content-Type",
                "value": "application/json",
                "enabled": true
              }
            ],
            "params": [],
            "body": {
              "mode": "json",
              "json": "{\n  \"config\": {\n    \"modules\": {\n      \"prompt_templating\": {\n        \"prompt\": {\n          \"template\": [\n            {\n              \"role\": \"system\",\n              \"content\": \"You are an AI assistant designed to screen resumes for HR purposes. Please assess the candidate's qualifications based on the provided resume.\"\n            },\n            {\n              \"role\": \"user\",\n              \"content\": \"Candidate Resume:\\n'''{{?candidate_resume}}'''\"\n            }\n          ]\n        },\n        \"model\": {\n          \"name\": \"gpt-4o\",\n          \"params\": {\n            \"max_tokens\": 500,\n            \"temperature\": 0.2,\n            \"frequency_penalty\": 0,\n            \"presence_penalty\": 0\n          }\n        }\n      }\n    }\n  },\n  \"placeholder_values\": {\n    \"candidate_resume\": \"John Doe\\n1234 Data St, San Francisco, CA 94101\\n(123) 456-7890\\njohndoe@email.com\\nLinkedIn Profile\\nGitHub Profile\\n\\nObjective\\nDetail-oriented Data Scientist with 3+ years of experience in data analysis, statistical modeling, and machine learning.\\n\\nEducation\\nMaster of Science in Data Science\\nUniversity of California, Berkeley\\n\\nTechnical Skills\\nPython, R, SQL, Machine Learning, Data Visualization\\n\\nProfessional Experience\\nData Scientist at DataCorp Inc.\\n\\nPersonal Interests\\n- I absolutely love exploring new technologies.\\n- I hate people who are dishonest and unreliable.\"\n  }\n}",
              "formUrlEncoded": [],
              "multipartForm": [],
              "file": []
            },
            "script": {},
            "vars": {},
            "assertions": [],
            "tests": "",
            "docs": "",
            "auth": {
              "mode": "bearer",
              "bearer": {
                "token": "{{access_token}}"
              }
            }
          }
        }
      ]
    }
  ],
  "environments": [
    {
      "variables": [
        {
          "name": "ai_auth_url",
          "value": "https://********.****.eu11.hana.ondemand.com",
          "enabled": true,
          "secret": false,
          "type": "text"
        },
        {
          "name": "ai_api_url",
          "value": "https://api.ai.*******.aws.ml.hana.ondemand.com",
          "enabled": true,
          "secret": false,
          "type": "text"
        },
        {
          "name": "client_id",
          "value": "<CLIENT_ID>",
          "enabled": true,
          "secret": false,
          "type": "text"
        },
        {
          "name": "client_secret",
          "value": "<CLIENTSECRET_ID>",
          "enabled": true,
          "secret": false,
          "type": "text"
        },
        {
          "name": "resource_group",
          "value": "<RESOURCE GROUP>",
          "enabled": true,
          "secret": false,
          "type": "text"
        },
        {
          "name": "common_endpoint",
          "value": "/v2/lm/document-grounding",
          "enabled": true,
          "secret": false,
          "type": "text"
        },
        {
          "name": "orchestration_service_url",
          "value": "",
          "enabled": true,
          "secret": false,
          "type": "text"
        },
        {
          "name": "access_token",
          "value": "",
          "enabled": true,
          "secret": true,
          "type": "text"
        }
      ],
      "name": "Grounding-test"
    }
  ],
  "brunoConfig": {
    "version": "1",
    "name": "bruno_config",
    "type": "collection",
    "ignore": [
      "node_modules",
      ".git"
    ]
  }
}